azure/LICENSE
azure/__init__.py
azure/azure.tcl
azure/example.py
azure/icon.png
azure/theme/dark.tcl
azure/theme/light.tcl
azure/theme/dark/box-accent.png
azure/theme/dark/box-basic.png
azure/theme/dark/box-hover.png
azure/theme/dark/box-invalid.png
azure/theme/dark/button-hover.png
azure/theme/dark/card.png
azure/theme/dark/check-accent.png
azure/theme/dark/check-basic.png
azure/theme/dark/check-hover.png
azure/theme/dark/check-tri-accent.png
azure/theme/dark/check-tri-basic.png
azure/theme/dark/check-tri-hover.png
azure/theme/dark/circle-accent.png
azure/theme/dark/circle-basic.png
azure/theme/dark/circle-hover.png
azure/theme/dark/combo-button-basic.png
azure/theme/dark/combo-button-focus.png
azure/theme/dark/combo-button-hover.png
azure/theme/dark/down-accent.png
azure/theme/dark/down.png
azure/theme/dark/empty.png
azure/theme/dark/hor-accent.png
azure/theme/dark/hor-basic.png
azure/theme/dark/hor-hover.png
azure/theme/dark/notebook.png
azure/theme/dark/off-basic.png
azure/theme/dark/on-accent.png
azure/theme/dark/on-basic.png
azure/theme/dark/outline-basic.png
azure/theme/dark/outline-hover.png
azure/theme/dark/radio-accent.png
azure/theme/dark/radio-basic.png
azure/theme/dark/radio-hover.png
azure/theme/dark/radio-tri-accent.png
azure/theme/dark/radio-tri-basic.png
azure/theme/dark/radio-tri-hover.png
azure/theme/dark/rect-accent-hover.png
azure/theme/dark/rect-accent.png
azure/theme/dark/rect-basic.png
azure/theme/dark/rect-hover.png
azure/theme/dark/right.png
azure/theme/dark/scale-hor.png
azure/theme/dark/scale-vert.png
azure/theme/dark/separator.png
azure/theme/dark/size.png
azure/theme/dark/tab-basic.png
azure/theme/dark/tab-disabled.png
azure/theme/dark/tab-hover.png
azure/theme/dark/tick-hor-accent.png
azure/theme/dark/tick-hor-basic.png
azure/theme/dark/tick-hor-hover.png
azure/theme/dark/tick-vert-accent.png
azure/theme/dark/tick-vert-basic.png
azure/theme/dark/tick-vert-hover.png
azure/theme/dark/tree-basic.png
azure/theme/dark/tree-pressed.png
sysmon_pytk-0.5.1.post1.dist-info/LICENSE
sysmon_pytk-0.5.1.post1.dist-info/METADATA
sysmon_pytk-0.5.1.post1.dist-info/WHEEL
sysmon_pytk-0.5.1.post1.dist-info/entry_points.txt
sysmon_pytk-0.5.1.post1.dist-info/top_level.txt
sysmon_pytk-0.5.1.post1.dist-info/RECORD
