Metadata-Version: 2.1
Name: sysmon_pytk
Version: 0.5.1.post1
Summary: System monitor app using Tkinter
Author-email: Stacey Adams <stacey.belle.rose@gmail.com>
License: MIT License
Project-URL: Homepage, https://github.com/staceybellerose/sysmon-pytk
Project-URL: Documentation, https://staceybellerose.github.io/sysmon-pytk/
Project-URL: Repository, https://github.com/staceybellerose/sysmon-pytk
Project-URL: Issues, https://github.com/staceybellerose/sysmon-pytk/issues
Keywords: system monitor
Classifier: Development Status :: 4 - Beta
Classifier: Intended Audience :: Developers
Classifier: Intended Audience :: End Users/Desktop
Classifier: Intended Audience :: System Administrators
Classifier: Environment :: Console
Classifier: Environment :: X11 Applications
Classifier: License :: OSI Approved :: MIT License
Classifier: Programming Language :: Python
Classifier: Programming Language :: Python :: 3
Classifier: Programming Language :: Python :: 3.9
Classifier: Programming Language :: Python :: 3.10
Classifier: Programming Language :: Python :: 3.11
Classifier: Programming Language :: Python :: 3.12
Classifier: Topic :: System :: Monitoring
Requires-Python: >=3.9
License-File: LICENSE
Requires-Dist: blessings >=1.7
Requires-Dist: darkdetect ==0.8.0
Requires-Dist: platformdirs >=4.2
Requires-Dist: psutil <6.0,>=5.8.0
Requires-Dist: typing-extensions >=4.10
